LICENSE
MANIFEST.in
README.rst
setup.py
hgdiffmetrics/__init__.py
hgdiffmetrics/hooks.py
hgdiffmetrics.egg-info/PKG-INFO
hgdiffmetrics.egg-info/SOURCES.txt
hgdiffmetrics.egg-info/dependency_links.txt
hgdiffmetrics.egg-info/requires.txt
hgdiffmetrics.egg-info/top_level.txt