Metadata-Version: 1.1
Name: hgdiffmetrics
Version: 1.0
Summary: Mercurial extension for using diffmetrics
Home-page: https://bitbucket.org/nfinne/hgdiffmetrics
Author: Neal Finne
Author-email: neal@nealfinne.com
License: UNKNOWN
Platform: UNKNOWN
Classifier: Environment :: Console
Classifier: Intended Audience :: Developers
Classifier: License :: OSI Approved :: GNU General Public License v2 or later (GPLv2+)
Classifier: Programming Language :: Python
Classifier: Programming Language :: Python :: 2
Classifier: Programming Language :: Python :: 3
Classifier: Topic :: Software Development :: Libraries :: Python Modules
Classifier: Topic :: Software Development :: Quality Assurance
